Squidiff/setup.py
Squidiff/train_squidiff.py
Squidiff/Squidiff/MLPModel.py
Squidiff/Squidiff/__init__.py
Squidiff/Squidiff/diffusion.py
Squidiff/Squidiff/dist_util.py
Squidiff/Squidiff/fp16_util.py
Squidiff/Squidiff/logger.py
Squidiff/Squidiff/losses.py
Squidiff/Squidiff/nn.py
Squidiff/Squidiff/resample.py
Squidiff/Squidiff/respace.py
Squidiff/Squidiff/script_util.py
Squidiff/Squidiff/scrna_datasets.py
Squidiff/Squidiff/train_util.py
Squidiff-1.0.7.dist-info/LICENSE
Squidiff-1.0.7.dist-info/METADATA
Squidiff-1.0.7.dist-info/WHEEL
Squidiff-1.0.7.dist-info/entry_points.txt
Squidiff-1.0.7.dist-info/top_level.txt
Squidiff-1.0.7.dist-info/RECORD
