Metadata-Version: 2.2
Name: Squidiff
Version: 1.0.7
Summary: Diffusion model-based generative framework designed to predict transcriptomic changes across diverse cell types in response to a wide range of environmental changes.
Author-email: Siyu He <siyuhe@stanford.edu>
License: BSD 3-Clause License
Requires-Python: >=3.8
License-File: LICENSE
Provides-Extra: gui
Requires-Dist: PyQt5; extra == "gui"
Provides-Extra: cli
Requires-Dist: rich; extra == "cli"
Requires-Dist: click; extra == "cli"
